markdown_pytest.py
markdown_pytest-0.3.1.dist-info/LICENSE
markdown_pytest-0.3.1.dist-info/METADATA
markdown_pytest-0.3.1.dist-info/WHEEL
markdown_pytest-0.3.1.dist-info/entry_points.txt
markdown_pytest-0.3.1.dist-info/RECORD
