Metadata-Version: 2.1
Name: markdown-pytest
Version: 0.3.1
Summary: Pytest plugin for runs tests directly from Markdown files
Home-page: https://github.com/mosquito/markdown-pytest
License: Apache-2.0
Keywords: pytest,markdown,documentation
Author: Dmitry Orlov
Author-email: me@mosquito.su
Requires-Python: >=3.8,<4.0
Classifier: Development Status :: 4 - Beta
Classifier: Environment :: Plugins
Classifier: Framework :: Pytest
Classifier: Intended Audience :: Developers
Classifier: License :: OSI Approved :: Apache Software License
Classifier: Natural Language :: English
Classifier: Operating System :: MacOS
Classifier: Operating System :: Microsoft
Classifier: Operating System :: POSIX
Classifier: Programming Language :: Python
Classifier: Programming Language :: Python :: 3
Classifier: Programming Language :: Python :: 3.8
Classifier: Programming Language :: Python :: 3.9
Classifier: Programming Language :: Python :: 3.10
Classifier: Programming Language :: Python :: 3.11
Classifier: Programming Language :: Python :: 3.12
Classifier: Programming Language :: Python :: 3 :: Only
Classifier: Programming Language :: Python :: Implementation :: CPython
Classifier: Programming Language :: Python :: Implementation :: PyPy
Classifier: Topic :: Software Development
Classifier: Topic :: Software Development :: Libraries
Requires-Dist: pytest-subtests (>=0.12.0)
Project-URL: Documentation, https://github.com/mosquito/markdown-pytest/blob/master/README.rst
Project-URL: Source, https://github.com/mosquito/markdown-pytest
Project-URL: Tracker, https://github.com/mosquito/markdown-pytest/issues
